odoo/addons/l10n_be_intrastat_product/README.rst
odoo/addons/l10n_be_intrastat_product/__init__.py
odoo/addons/l10n_be_intrastat_product/__manifest__.py
odoo/addons/l10n_be_intrastat_product/data/intrastat_region.xml
odoo/addons/l10n_be_intrastat_product/data/intrastat_transaction.xml
odoo/addons/l10n_be_intrastat_product/doc/intrastat_manual_basis_en.pdf
odoo/addons/l10n_be_intrastat_product/i18n/l10n_be_intrastat_product.pot
odoo/addons/l10n_be_intrastat_product/models/__init__.py
odoo/addons/l10n_be_intrastat_product/models/account_move.py
odoo/addons/l10n_be_intrastat_product/models/l10n_be_intrastat_product_declaration.py
odoo/addons/l10n_be_intrastat_product/readme/CONFIGURE.rst
odoo/addons/l10n_be_intrastat_product/readme/CONTRIBUTORS.rst
odoo/addons/l10n_be_intrastat_product/readme/DESCRIPTION.rst
odoo/addons/l10n_be_intrastat_product/readme/HISTORY.rst
odoo/addons/l10n_be_intrastat_product/readme/INSTALL.rst
odoo/addons/l10n_be_intrastat_product/readme/ROADMAP.rst
odoo/addons/l10n_be_intrastat_product/security/intrastat_security.xml
odoo/addons/l10n_be_intrastat_product/security/ir.model.access.csv
odoo/addons/l10n_be_intrastat_product/static/data/2023_de_intrastat_codes.csv
odoo/addons/l10n_be_intrastat_product/static/data/2023_en_intrastat_codes.csv
odoo/addons/l10n_be_intrastat_product/static/data/2023_fr_intrastat_codes.csv
odoo/addons/l10n_be_intrastat_product/static/data/2023_nl_intrastat_codes.csv
odoo/addons/l10n_be_intrastat_product/static/data/ex19e.xsd
odoo/addons/l10n_be_intrastat_product/static/data/ex19s.xsd
odoo/addons/l10n_be_intrastat_product/static/data/intrastat_x_e.xsd
odoo/addons/l10n_be_intrastat_product/static/data/intrastat_x_s.xsd
odoo/addons/l10n_be_intrastat_product/static/description/icon.png
odoo/addons/l10n_be_intrastat_product/static/description/index.html
odoo/addons/l10n_be_intrastat_product/tests/__init__.py
odoo/addons/l10n_be_intrastat_product/tests/test_intrastat_be.py
odoo14_addon_l10n_be_intrastat_product-14.0.1.2.0.dist-info/METADATA
odoo14_addon_l10n_be_intrastat_product-14.0.1.2.0.dist-info/WHEEL
odoo14_addon_l10n_be_intrastat_product-14.0.1.2.0.dist-info/top_level.txt
odoo14_addon_l10n_be_intrastat_product-14.0.1.2.0.dist-info/RECORD
